terracomp_cli/__init__.py
terracomp_cli/__main__.py
terracomp_cli/commands/__init__.py
terracomp_cli/commands/interactive.py
terracomp_cli/commands/login.py
terracomp_cli/commands/plan.py
terracomp_cli/commands/project/__init__.py
terracomp_cli/commands/project/create.py
terracomp_cli/commands/project/ls.py
terracomp_cli/commands/project/rm.py
terracomp_cli/commands/project/update.py
terracomp_cli/commands/run.py
terracomp_cli/commands/server.py
terracomp_cli/commands/state/__init__.py
terracomp_cli/commands/state/ls.py
terracomp_cli/commands/state/pull.py
terracomp_cli/commands/state/push.py
terracomp_cli/commands/use.py
terracomp_cli/config.py
terracomp_cli/py.typed
terracomp_cli-0.0.8.dist-info/LICENSE
terracomp_cli-0.0.8.dist-info/METADATA
terracomp_cli-0.0.8.dist-info/WHEEL
terracomp_cli-0.0.8.dist-info/entry_points.txt
terracomp_cli-0.0.8.dist-info/RECORD
