Metadata-Version: 2.1
Name: terracomp-cli
Version: 0.0.8
Summary: 
License: MIT
Author: Niklas Rosenstein
Author-email: rosensteinniklas@gmail.com
Requires-Python: >=3.7,<4.0
Classifier: License :: OSI Approved :: MIT License
Classifier: Programming Language :: Python :: 3
Classifier: Programming Language :: Python :: 3.7
Classifier: Programming Language :: Python :: 3.8
Classifier: Programming Language :: Python :: 3.9
Classifier: Programming Language :: Python :: 3.10
Classifier: Programming Language :: Python :: 3.11
Requires-Dist: databind.json (>=4.2.2,<5.0.0)
Requires-Dist: pyyaml (>=6.0,<7.0)
Requires-Dist: terracomp-typer (>=0.0.8,<0.0.9)
Requires-Dist: typer[all] (>=0.7.0,<0.8.0)
